NiukeWangHulianwangXiaozhaoDalibao2021Fix1/README.md
NiukeWangHulianwangXiaozhaoDalibao2021Fix1/__init__.py
NiukeWangHulianwangXiaozhaoDalibao2021Fix1/__main__.py
NiukeWangHulianwangXiaozhaoDalibao2021Fix1/file.epub
NiukeWangHulianwangXiaozhaoDalibao2021Fix1/index.html
NiukeWangHulianwangXiaozhaoDalibao2021Fix1/css/__init__.py
NiukeWangHulianwangXiaozhaoDalibao2021Fix1/css/annotations.css
NiukeWangHulianwangXiaozhaoDalibao2021Fix1/css/main.css
NiukeWangHulianwangXiaozhaoDalibao2021Fix1/css/normalize.css
NiukeWangHulianwangXiaozhaoDalibao2021Fix1/css/popup.css
NiukeWangHulianwangXiaozhaoDalibao2021Fix1/font/__init__.py
NiukeWangHulianwangXiaozhaoDalibao2021Fix1/font/fontello.eot
NiukeWangHulianwangXiaozhaoDalibao2021Fix1/font/fontello.svg
NiukeWangHulianwangXiaozhaoDalibao2021Fix1/font/fontello.ttf
NiukeWangHulianwangXiaozhaoDalibao2021Fix1/font/fontello.woff
NiukeWangHulianwangXiaozhaoDalibao2021Fix1/img/__init__.py
NiukeWangHulianwangXiaozhaoDalibao2021Fix1/img/annotator-glyph-sprite.png
NiukeWangHulianwangXiaozhaoDalibao2021Fix1/img/annotator-icon-sprite.png
NiukeWangHulianwangXiaozhaoDalibao2021Fix1/img/apple-touch-icon.png
NiukeWangHulianwangXiaozhaoDalibao2021Fix1/img/cancelfullscreen.png
NiukeWangHulianwangXiaozhaoDalibao2021Fix1/img/close.png
NiukeWangHulianwangXiaozhaoDalibao2021Fix1/img/fullscreen.png
NiukeWangHulianwangXiaozhaoDalibao2021Fix1/img/loader.gif
NiukeWangHulianwangXiaozhaoDalibao2021Fix1/img/menu-icon.png
NiukeWangHulianwangXiaozhaoDalibao2021Fix1/img/save.png
NiukeWangHulianwangXiaozhaoDalibao2021Fix1/img/saved.png
NiukeWangHulianwangXiaozhaoDalibao2021Fix1/img/settings-s.png
NiukeWangHulianwangXiaozhaoDalibao2021Fix1/img/settings.png
NiukeWangHulianwangXiaozhaoDalibao2021Fix1/img/star.png
NiukeWangHulianwangXiaozhaoDalibao2021Fix1/js/__init__.py
NiukeWangHulianwangXiaozhaoDalibao2021Fix1/js/epub.js
NiukeWangHulianwangXiaozhaoDalibao2021Fix1/js/epub.min.js
NiukeWangHulianwangXiaozhaoDalibao2021Fix1/js/epub.min.map
niuke_wang_hulianwang_xiaozhao_dalibao_2021_fix1-2025.3.25.1.dist-info/METADATA
niuke_wang_hulianwang_xiaozhao_dalibao_2021_fix1-2025.3.25.1.dist-info/WHEEL
niuke_wang_hulianwang_xiaozhao_dalibao_2021_fix1-2025.3.25.1.dist-info/entry_points.txt
niuke_wang_hulianwang_xiaozhao_dalibao_2021_fix1-2025.3.25.1.dist-info/top_level.txt
niuke_wang_hulianwang_xiaozhao_dalibao_2021_fix1-2025.3.25.1.dist-info/RECORD
